traceforward/__init__.py
traceforward/__main__.py
traceforward/cli.py
traceforward/config.py
traceforward/command/__init__.py
traceforward/command/traceroute.py
traceforward/forward_server/__init__.py
traceforward/forward_server/client.py
traceforward/utils/__init__.py
traceforward/utils/helpers.py
traceforward-0.0.3.dist-info/LICENSE
traceforward-0.0.3.dist-info/METADATA
traceforward-0.0.3.dist-info/WHEEL
traceforward-0.0.3.dist-info/entry_points.txt
traceforward-0.0.3.dist-info/top_level.txt
traceforward-0.0.3.dist-info/RECORD
