Metadata-Version: 2.1
Name: traceforward
Version: 0.0.3
Summary: Forward Networks traceroute utility
Author-email: Peyman Kazemian <peymankazemian@forwardnetworks.com>, Kostiantyn Fedorenko <kostiantynfedorenko@forwardnetworks.com>, Billy Chen <billychen@forwardnetworks.com>, Wendy Tang <wendytang@forwardnetworks.com>, Abhishek Jha <abhishekjha@forwardnetworks.com>
Project-URL: Homepage, https://github.com/forwardnetworks/TraceForward
Classifier: Programming Language :: Python :: 3
Classifier: License :: OSI Approved :: MIT License
Classifier: Operating System :: OS Independent
Requires-Python: >=3.9
License-File: LICENSE
Requires-Dist: requests
Requires-Dist: urllib3 ==1.26.15
